orbitdb_kit_py/__init__.py
orbitdb_kit_py/config.py
orbitdb_kit_py/orbitdb_kit.py
orbitdb_kit_py/orbitdb_kit_lib.py
orbitdb_kit_py/websocket_kit.py
orbitdb_kit_py/websocket_kit_lib.py
orbitdb_kit_py-0.0.9.dist-info/LICENSE
orbitdb_kit_py-0.0.9.dist-info/METADATA
orbitdb_kit_py-0.0.9.dist-info/WHEEL
orbitdb_kit_py-0.0.9.dist-info/top_level.txt
orbitdb_kit_py-0.0.9.dist-info/RECORD
