Metadata-Version: 2.1
Name: orbitdb_kit_py
Version: 0.0.9
Summary: a python wrapper around nodejs orbitdb
Author-email: Benjamin Barber <starworks5@gmail.com>
Project-URL: Homepage, https://github.com/endomorphosis/orbitdb_kit
Project-URL: Issues, https://github.com/endomorphosis/orbitdb_kit/issues
Classifier: Programming Language :: Python :: 3
Classifier: License :: OSI Approved :: GNU Affero General Public License v3 or later (AGPLv3+)
Classifier: Operating System :: POSIX :: Linux
Requires-Python: >=3.8
License-File: LICENSE
